netplotbrain/__init__.py
netplotbrain/__version.py
netplotbrain/plot.py
netplotbrain/derive/__init__.py
netplotbrain/derive/from_bids.py
netplotbrain/example_data/example_edges.tsv
netplotbrain/example_data/example_nodes.tsv
netplotbrain/example_data/bids_test/.bidsignore
netplotbrain/example_data/bids_test/README.md
netplotbrain/example_data/bids_test/dataset_description.json
netplotbrain/example_data/bids_test/generate_data.py
netplotbrain/example_data/bids_test/participants.tsv
netplotbrain/example_data/bids_test/derivatives/connectivity/dataset_description.json
netplotbrain/example_data/bids_test/derivatives/connectivity/sub-001/ses-post/func/sub-001_ses-post_task-a_relmat.tsv
netplotbrain/example_data/bids_test/derivatives/connectivity/sub-001/ses-post/func/sub-001_ses-post_task-b_relmat.tsv
netplotbrain/example_data/bids_test/derivatives/connectivity/sub-001/ses-pre/func/sub-001_ses-pre_task-a_relmat.tsv
netplotbrain/example_data/bids_test/derivatives/connectivity/sub-001/ses-pre/func/sub-001_ses-pre_task-b_relmat.tsv
netplotbrain/example_data/bids_test/derivatives/connectivity/sub-002/ses-post/func/sub-002_ses-post_task-a_relmat.tsv
netplotbrain/example_data/bids_test/derivatives/connectivity/sub-002/ses-post/func/sub-002_ses-post_task-b_relmat.tsv
netplotbrain/example_data/bids_test/derivatives/connectivity/sub-002/ses-pre/func/sub-002_ses-pre_task-a_relmat.tsv
netplotbrain/example_data/bids_test/derivatives/connectivity/sub-002/ses-pre/func/sub-002_ses-pre_task-b_relmat.tsv
netplotbrain/example_data/bids_test/derivatives/connectivity/sub-003/ses-post/func/sub-003_ses-post_task-a_relmat.tsv
netplotbrain/example_data/bids_test/derivatives/connectivity/sub-003/ses-post/func/sub-003_ses-post_task-b_relmat.tsv
netplotbrain/example_data/bids_test/derivatives/connectivity/sub-003/ses-pre/func/sub-003_ses-pre_task-a_relmat.tsv
netplotbrain/example_data/bids_test/derivatives/connectivity/sub-003/ses-pre/func/sub-003_ses-pre_task-b_relmat.tsv
netplotbrain-0.3.0.dist-info/LICENSE
netplotbrain-0.3.0.dist-info/METADATA
netplotbrain-0.3.0.dist-info/WHEEL
netplotbrain-0.3.0.dist-info/top_level.txt
netplotbrain-0.3.0.dist-info/RECORD
